magic_flow/__init__.py
magic_flow/account_key.py
magic_flow/cadence/__init__.py
magic_flow/cadence/address.py
magic_flow/cadence/composite.py
magic_flow/cadence/constants.py
magic_flow/cadence/decode.py
magic_flow/cadence/encode.py
magic_flow/cadence/kind.py
magic_flow/cadence/kinds.py
magic_flow/cadence/simple_kinds.py
magic_flow/cadence/types.py
magic_flow/cadence/value.py
magic_flow/client/__init__.py
magic_flow/client/client.py
magic_flow/client/entities.py
magic_flow/exceptions.py
magic_flow/frlp/__init__.py
magic_flow/frlp/utils.py
magic_flow/proto/__init__.py
magic_flow/proto/access/__init__.py
magic_flow/proto/entities/__init__.py
magic_flow/proto/execution/__init__.py
magic_flow/proto/flow/__init__.py
magic_flow/proto/flow/access/__init__.py
magic_flow/proto/flow/entities/__init__.py
magic_flow/proto/flow/entities.py
magic_flow/proto/flow/execution/__init__.py
magic_flow/proto/google/__init__.py
magic_flow/proto/google/protobuf/__init__.py
magic_flow/proto/message_pool.py
magic_flow/proto/py.typed
magic_flow/script.py
magic_flow/signer/__init__.py
magic_flow/signer/hash_algo.py
magic_flow/signer/in_memory_signer.py
magic_flow/signer/in_memory_verifier.py
magic_flow/signer/sign_algo.py
magic_flow/signer/signer.py
magic_flow/signer/verifier.py
magic_flow/templates.py
magic_flow/tx.py
magic_flow/utils/__init__.py
magic_flow/utils/verify_user_signature.py
magic_flow-0.1.11.dist-info/METADATA
magic_flow-0.1.11.dist-info/WHEEL
magic_flow-0.1.11.dist-info/entry_points.txt
magic_flow-0.1.11.dist-info/licenses/LICENSE
magic_flow-0.1.11.dist-info/RECORD
