Metadata-Version: 2.4
Name: magic-flow
Version: 0.1.11
Summary: Python SDK for the Flow blockchain with updated dependencies and Python 3.13 support
License: MIT
License-File: LICENSE
Author: Janez Podhostnik
Author-email: janez.podhostnik@gmail.com
Requires-Python: >=3.10,<4.0
Classifier: License :: OSI Approved :: MIT License
Classifier: Programming Language :: Python :: 3
Classifier: Programming Language :: Python :: 3.10
Classifier: Programming Language :: Python :: 3.11
Classifier: Programming Language :: Python :: 3.12
Classifier: Programming Language :: Python :: 3.13
Classifier: Programming Language :: Python :: 3.14
Requires-Dist: backrefs (>=6.0.1,<7.0.0)
Requires-Dist: betterproto2 (>=0.9.0,<0.10.0)
Requires-Dist: ecdsa (>=v0.19,<0.20)
Requires-Dist: grpcio (>=1.75,<2.0)
Requires-Dist: grpcio-tools (>=1.65,<2.0)
Requires-Dist: pydantic-core (>=2.18.0)
Requires-Dist: rlp (>=4.0,<5.0)
Project-URL: Repository, https://github.com/magiclabs/magic-flow-python
